motalk/__init__.py
motalk-0.1.0.dist-info/licenses/LICENSE
motalk-0.1.0.dist-info/METADATA
motalk-0.1.0.dist-info/WHEEL
motalk-0.1.0.dist-info/top_level.txt
motalk-0.1.0.dist-info/RECORD
